custom_text_classification_tool/__init__.py
custom_text_classification_tool/language_utils/__init__.py
custom_text_classification_tool/language_utils/language_client.py
custom_text_classification_tool/language_utils/language_formatter_utils.py
custom_text_classification_tool/language_utils/language_mode.py
custom_text_classification_tool/language_utils/language_parser_utils.py
custom_text_classification_tool/language_utils/language_skill.py
custom_text_classification_tool/language_utils/language_tool_utils.py
custom_text_classification_tool/tools/__init__.py
custom_text_classification_tool/tools/custom_text_classification.py
custom_text_classification_tool/tools/utils.py
custom_text_classification_tool/yamls/custom_text_classification.yaml
tests/__init__.py
tests/test_custom_text_classification_tool.py
promptflow_azure_ai_language_custom_text_classification-1.0.0.dist-info/METADATA
promptflow_azure_ai_language_custom_text_classification-1.0.0.dist-info/WHEEL
promptflow_azure_ai_language_custom_text_classification-1.0.0.dist-info/entry_points.txt
promptflow_azure_ai_language_custom_text_classification-1.0.0.dist-info/RECORD
