Metadata-Version: 2.1
Name: promptflow-azure-ai-language-custom-text-classification
Version: 1.0.0
Summary: Use Azure AI Language to generate abstractive summaries of documents.
License: MIT
Author: Federico Rapetti
Author-email: f.rapetti@reply.it
Requires-Python: >=3.8,<4.0
Classifier: License :: OSI Approved :: MIT License
Classifier: Programming Language :: Python :: 3
Classifier: Programming Language :: Python :: 3.8
Classifier: Programming Language :: Python :: 3.9
Classifier: Programming Language :: Python :: 3.10
Classifier: Programming Language :: Python :: 3.11
Classifier: Programming Language :: Python :: 3.12
Requires-Dist: promptflow (>=1.5.0,<2.0.0)
Requires-Dist: requests (>=2.31.0,<3.0.0)
Requires-Dist: ruamel-yaml (>=0.18.6,<0.19.0)
